codeinterpreterapi_hyperobjekt/__init__.py
codeinterpreterapi_hyperobjekt/agents/__init__.py
codeinterpreterapi_hyperobjekt/agents/custom_agent.py
codeinterpreterapi_hyperobjekt/agents/functions_agent.py
codeinterpreterapi_hyperobjekt/chains/__init__.py
codeinterpreterapi_hyperobjekt/chains/extract_code.py
codeinterpreterapi_hyperobjekt/chains/modifications_check.py
codeinterpreterapi_hyperobjekt/chains/rm_dl_link.py
codeinterpreterapi_hyperobjekt/chat_history.py
codeinterpreterapi_hyperobjekt/config.py
codeinterpreterapi_hyperobjekt/parser.py
codeinterpreterapi_hyperobjekt/prompts/__init__.py
codeinterpreterapi_hyperobjekt/prompts/modifications_check.py
codeinterpreterapi_hyperobjekt/prompts/remove_dl_link.py
codeinterpreterapi_hyperobjekt/prompts/system_message.py
codeinterpreterapi_hyperobjekt/schema/__init__.py
codeinterpreterapi_hyperobjekt/schema/file.py
codeinterpreterapi_hyperobjekt/schema/input.py
codeinterpreterapi_hyperobjekt/schema/response.py
codeinterpreterapi_hyperobjekt/schema/status.py
codeinterpreterapi_hyperobjekt/session.py
codeinterpreterapi_hyperobjekt-0.0.16.dist-info/LICENSE
codeinterpreterapi_hyperobjekt-0.0.16.dist-info/METADATA
codeinterpreterapi_hyperobjekt-0.0.16.dist-info/WHEEL
codeinterpreterapi_hyperobjekt-0.0.16.dist-info/RECORD
