Metadata-Version: 2.1
Name: codeinterpreterapi_hyperobjekt
Version: 0.0.16
Summary: CodeInterpreterAPI is an (unofficial) open source python interface for the ChatGPT CodeInterpreter.
Home-page: https://github.com/hyperobjekt/code-interpreter
License: MIT
Keywords: codeinterpreter_hyperobjekt,chatgpt,codeinterpreterapi_hyperobjekt,api,langchain,codeboxapi
Author: Hyperobjekt
Author-email: info@hyperobjekt.com
Requires-Python: >=3.9, !=2.7.*, !=3.0.*, !=3.1.*, !=3.2.*, !=3.3.*, !=3.4.*, !=3.5.*, !=3.6.*, !=3.7.*, !=3.8.*
Classifier: License :: OSI Approved :: MIT License
Classifier: Programming Language :: Python :: 3
Classifier: Programming Language :: Python :: 3.9
Classifier: Programming Language :: Python :: 3.10
Classifier: Programming Language :: Python :: 3.11
Provides-Extra: all
Provides-Extra: frontend
Provides-Extra: image-support
Provides-Extra: localbox
Requires-Dist: Pillow (>=9,<10) ; extra == "all" or extra == "image-support"
Requires-Dist: codeboxapi (>=0.0.18)
Requires-Dist: jupyter-kernel-gateway (>=2,<3) ; extra == "all" or extra == "localbox"
Requires-Dist: langchain (>=0.0.242,<0.0.243)
Requires-Dist: openai (>=0.27,<0.28)
Requires-Dist: python-dotenv (>=1,<2)
Requires-Dist: streamlit (>=1,<2) ; extra == "all" or extra == "frontend"
Project-URL: Repository, https://github.com/hyperobjekt/code-interpreter
